archaea_core/__init__.py
archaea_core/archaea.py
archaea_core/base.py
archaea_core/constants.py
archaea_core/exceptions.py
archaea_core/llm.py
archaea_core/namespace.py
archaea_core/operate.py
archaea_core/orchestration.py
archaea_core/prompt.py
archaea_core/rerank.py
archaea_core/types.py
archaea_core/utils.py
archaea_core/utils_graph.py
archaea_core/version.py
archaea_core/kg/__init__.py
archaea_core/kg/faiss_impl.py
archaea_core/kg/json_doc_status_impl.py
archaea_core/kg/json_kv_impl.py
archaea_core/kg/memgraph_impl.py
archaea_core/kg/milvus_impl.py
archaea_core/kg/mongo_impl.py
archaea_core/kg/nano_vector_db_impl.py
archaea_core/kg/neo4j_impl.py
archaea_core/kg/networkx_impl.py
archaea_core/kg/postgres_impl.py
archaea_core/kg/qdrant_impl.py
archaea_core/kg/redis_impl.py
archaea_core/kg/shared_storage.py
archaea_core/llm/__init__.py
archaea_core/llm/anthropic.py
archaea_core/llm/azure_openai.py
archaea_core/llm/bedrock.py
archaea_core/llm/hf.py
archaea_core/llm/jina.py
archaea_core/llm/llama_index_impl.py
archaea_core/llm/lmdeploy.py
archaea_core/llm/lollms.py
archaea_core/llm/nvidia_openai.py
archaea_core/llm/ollama.py
archaea_core/llm/openai.py
archaea_core/llm/siliconcloud.py
archaea_core/llm/zhipu.py
archaea_core/ragplus/__init__.py
archaea_core/ragplus/batch.py
archaea_core/ragplus/batch_parser.py
archaea_core/ragplus/config.py
archaea_core/ragplus/enhanced_markdown.py
archaea_core/ragplus/modalprocessors.py
archaea_core/ragplus/parser.py
archaea_core/ragplus/processor.py
archaea_core/ragplus/prompt.py
archaea_core/ragplus/query.py
archaea_core/ragplus/ragplus.py
archaea_core/ragplus/utils.py
libruntime/__init__.py
libruntime/pyarmor_runtime.pyd
archaea_core-2.0.0.dist-info/METADATA
archaea_core-2.0.0.dist-info/WHEEL
archaea_core-2.0.0.dist-info/top_level.txt
archaea_core-2.0.0.dist-info/RECORD
