Metadata-Version: 2.4
Name: archaea-core
Version: 2.0.0
Summary: Core RAG engine and multimodal processing library
Author: Archaea Team
Requires-Python: <3.14,>=3.10
Requires-Dist: asyncio-mqtt>=0.16.2
Requires-Dist: aiofiles
Requires-Dist: aiohttp
Requires-Dist: asyncpg
Requires-Dist: configparser
Requires-Dist: dotenv
Requires-Dist: python-dotenv
Requires-Dist: future
Requires-Dist: httpcore
Requires-Dist: httpx
Requires-Dist: jiter
Requires-Dist: pydantic
Requires-Dist: pydantic-settings
Requires-Dist: tenacity
Requires-Dist: typer>=0.16.0
Requires-Dist: numpy
Requires-Dist: pandas>=2.0.0
Requires-Dist: tiktoken
Requires-Dist: tqdm>=4.67.1
Requires-Dist: openai
Requires-Dist: anthropic>=0.57.1
Requires-Dist: ollama>=0.5.3
Requires-Dist: redis>=6.2.0
Requires-Dist: neo4j>=5.28.1
Requires-Dist: psycopg2-binary>=2.9.10
Requires-Dist: pymilvus>=2.3.4
Requires-Dist: pillow>=11.3.0
Requires-Dist: reportlab>=4.4.2
Requires-Dist: ingestar[core]>=0.1.2
Requires-Dist: pyuca
Requires-Dist: setuptools
Requires-Dist: ascii_colors
Requires-Dist: distro
Requires-Dist: psutil>=5.9.0
Requires-Dist: protobuf==3.20.0
Requires-Dist: pathspec>=0.12.1
Requires-Dist: gitpython>=3.1.44
Requires-Dist: pyyaml>=6.0.2
Requires-Dist: requests>=2.32.4
Requires-Dist: rich>=14.0.0
Provides-Extra: dev
Requires-Dist: pytest>=8.4.1; extra == "dev"
Requires-Dist: pytest-asyncio>=1.1.0; extra == "dev"
Requires-Dist: black>=23.0; extra == "dev"
Requires-Dist: isort>=5.12; extra == "dev"
Requires-Dist: flake8>=6.0; extra == "dev"
Requires-Dist: mypy>=1.0; extra == "dev"
